{"type_name": "UniformQuantizer", "serialized_value": {"n_bits": 8, "is_signed": true, "is_symmetric": false, "is_qat": false, "is_narrow": false, "is_precomputed_qat": false, "rmax": {"type_name": "numpy_float", "serialized_value": 7.9, "dtype": "float64"}, "rmin": {"type_name": "numpy_float", "serialized_value": 0.1, "dtype": "float64"}, "scale": {"type_name": "numpy_float", "serialized_value": 0.03058823529411765, "dtype": "float64"}, "zero_point": {"type_name": "numpy_integer", "serialized_value": -131, "dtype": "int64"}, "offset": 128, "no_clipping": false}}
